dockerode_api_proxy_client/__init__.py
dockerode_api_proxy_client/__version__.py
dockerode_api_proxy_client/client.py
dockerode_api_proxy_client/py.typed
dockerode_api_proxy_client/dto/__init__.py
dockerode_api_proxy_client/dto/container.py
dockerode_api_proxy_client/dto/image.py
dockerode_api_proxy_client/settings/__init__.py
dockerode_api_proxy_client/settings/env.py
dockerode_api_proxy_client/utils/__init__.py
dockerode_api_proxy_client/utils/datatype.py
dockerode_api_proxy_client/utils/formatting.py
dockerode_api_proxy_client/utils/get_authentication_header.py
dockerode_api_proxy_client-5.0.0.dist-info/LICENSE
dockerode_api_proxy_client-5.0.0.dist-info/METADATA
dockerode_api_proxy_client-5.0.0.dist-info/WHEEL
dockerode_api_proxy_client-5.0.0.dist-info/top_level.txt
dockerode_api_proxy_client-5.0.0.dist-info/RECORD
